odoo10_addon_web_widget_text_markdown-10.0.1.0.0-py2.7-nspkg.pth
odoo/addons/web_widget_text_markdown/README.rst
odoo/addons/web_widget_text_markdown/__init__.py
odoo/addons/web_widget_text_markdown/__manifest__.py
odoo/addons/web_widget_text_markdown/demo/bootstrap_markdown.xml
odoo/addons/web_widget_text_markdown/i18n/ar.po
odoo/addons/web_widget_text_markdown/i18n/de.po
odoo/addons/web_widget_text_markdown/i18n/es.po
odoo/addons/web_widget_text_markdown/i18n/fi.po
odoo/addons/web_widget_text_markdown/i18n/fr.po
odoo/addons/web_widget_text_markdown/i18n/pt_BR.po
odoo/addons/web_widget_text_markdown/i18n/sl.po
odoo/addons/web_widget_text_markdown/i18n/tr.po
odoo/addons/web_widget_text_markdown/static/description/icon.png
odoo/addons/web_widget_text_markdown/static/lib/bootstrap-markdown/bootstrap-markdown.js
odoo/addons/web_widget_text_markdown/static/lib/highlight/CHANGES.md
odoo/addons/web_widget_text_markdown/static/lib/highlight/LICENSE
odoo/addons/web_widget_text_markdown/static/lib/highlight/README.md
odoo/addons/web_widget_text_markdown/static/lib/highlight/README.ru.md
odoo/addons/web_widget_text_markdown/static/lib/highlight/highlight.min.js
odoo/addons/web_widget_text_markdown/static/lib/highlight/styles/arta.css
odoo/addons/web_widget_text_markdown/static/lib/highlight/styles/ascetic.css
odoo/addons/web_widget_text_markdown/static/lib/highlight/styles/atelier-dune.dark.css
odoo/addons/web_widget_text_markdown/static/lib/highlight/styles/atelier-dune.light.css
odoo/addons/web_widget_text_markdown/static/lib/highlight/styles/atelier-forest.dark.css
odoo/addons/web_widget_text_markdown/static/lib/highlight/styles/atelier-forest.light.css
odoo/addons/web_widget_text_markdown/static/lib/highlight/styles/atelier-heath.dark.css
odoo/addons/web_widget_text_markdown/static/lib/highlight/styles/atelier-heath.light.css
odoo/addons/web_widget_text_markdown/static/lib/highlight/styles/atelier-lakeside.dark.css
odoo10_addon_web_widget_text_markdown-10.0.1.0.0.dist-info/DESCRIPTION.rst
odoo10_addon_web_widget_text_markdown-10.0.1.0.0.dist-info/METADATA
odoo10_addon_web_widget_text_markdown-10.0.1.0.0.dist-info/RECORD
odoo10_addon_web_widget_text_markdown-10.0.1.0.0.dist-info/WHEEL
odoo10_addon_web_widget_text_markdown-10.0.1.0.0.dist-info/metadata.json
odoo10_addon_web_widget_text_markdown-10.0.1.0.0.dist-info/namespace_packages.txt
odoo10_addon_web_widget_text_markdown-10.0.1.0.0.dist-info/top_level.txt
